motorisedcameratracking/Cameras.py
motorisedcameratracking/Config.py
motorisedcameratracking/Imaging.cpython-37m-arm-linux-gnueabihf.so
motorisedcameratracking/MotorControl.py
motorisedcameratracking/MotorisedCameraTracking.py
motorisedcameratracking/__init__.py
motorisedcameratracking/errors.py
motorisedcameratracking-0.4.0.dist-info/LICENSE
motorisedcameratracking-0.4.0.dist-info/METADATA
motorisedcameratracking-0.4.0.dist-info/WHEEL
motorisedcameratracking-0.4.0.dist-info/top_level.txt
motorisedcameratracking-0.4.0.dist-info/RECORD
