Metadata-Version: 2.1
Name: motorisedcameratracking
Version: 0.4.0
Summary: Used to create a tracking tripod head
Home-page: https://github.com/wDove1/motorisedcameratracking
Author: William Dove
Author-email: williamtdove@gmail.com
License: Apache 2.0
Platform: UNKNOWN
Classifier: Programming Language :: Python :: 3
Classifier: Programming Language :: Python :: 3.7
Classifier: Programming Language :: Python :: 3.8
Classifier: License :: OSI Approved :: Apache Software License
Classifier: Operating System :: OS Independent
Requires-Python: >=3.7,<=3.8
Requires-Dist: cvlib
Requires-Dist: opencv-python
Requires-Dist: motorcontrollib
